silero_vad_lite/__init__.py
silero_vad_lite/silero_vad.py
silero_vad_lite/.dylibs/libonnxruntime.1.19.0.dylib
silero_vad_lite/data/silero_vad_lite.dylib
silero_vad_lite/data/silero_vad.onnx
silero_vad_lite/data/libonnxruntime.1.19.0.dylib
silero_vad_lite-0.2.1.dist-info/RECORD
silero_vad_lite-0.2.1.dist-info/LICENSE
silero_vad_lite-0.2.1.dist-info/WHEEL
silero_vad_lite-0.2.1.dist-info/top_level.txt
silero_vad_lite-0.2.1.dist-info/METADATA
